OCP-stubs/__init__.pyi
OCP-stubs/AIS/__init__.pyi
OCP-stubs/APIHeaderSection/__init__.pyi
OCP-stubs/Adaptor2d/__init__.pyi
OCP-stubs/Adaptor3d/__init__.pyi
OCP-stubs/AdvApp2Var/__init__.pyi
OCP-stubs/AdvApprox/__init__.pyi
OCP-stubs/AppBlend/__init__.pyi
OCP-stubs/AppCont/__init__.pyi
OCP-stubs/AppDef/__init__.pyi
OCP-stubs/AppParCurves/__init__.pyi
OCP-stubs/AppStd/__init__.pyi
OCP-stubs/AppStdL/__init__.pyi
OCP-stubs/Approx/__init__.pyi
OCP-stubs/Aspect/__init__.pyi
OCP-stubs/BOPAlgo/__init__.pyi
OCP-stubs/BOPDS/__init__.pyi
OCP-stubs/BOPTools/__init__.pyi
OCP-stubs/BRep/__init__.pyi
OCP-stubs/BRepAdaptor/__init__.pyi
OCP-stubs/BRepAlgo/__init__.pyi
OCP-stubs/BRepAlgoAPI/__init__.pyi
OCP-stubs/BRepApprox/__init__.pyi
OCP-stubs/BRepBlend/__init__.pyi
OCP-stubs/BRepBndLib/__init__.pyi
OCP-stubs/BRepBuilderAPI/__init__.pyi
OCP-stubs/BRepCheck/__init__.pyi
OCP-stubs/BRepClass/__init__.pyi
OCP-stubs/BRepClass3d/__init__.pyi
OCP-stubs/BRepExtrema/__init__.pyi
OCP-stubs/BRepFeat/__init__.pyi
OCP-stubs/BRepFill/__init__.pyi
OCP-stubs/BRepFilletAPI/__init__.pyi
OCP-stubs/BRepGProp/__init__.pyi
OCP-stubs/BRepIntCurveSurface/__init__.pyi
OCP-stubs/BRepLProp/__init__.pyi
OCP-stubs/BRepLib/__init__.pyi
OCP-stubs/BRepMAT2d/__init__.pyi
OCP-stubs/BRepMesh/__init__.pyi
OCP-stubs/BRepOffset/__init__.pyi
OCP-stubs/BRepOffsetAPI/__init__.pyi
OCP-stubs/BRepPrim/__init__.pyi
OCP-stubs/BRepPrimAPI/__init__.pyi
OCP-stubs/BRepProj/__init__.pyi
OCP-stubs/BRepSweep/__init__.pyi
OCP-stubs/BRepToIGES/__init__.pyi
OCP-stubs/BRepToIGESBRep/__init__.pyi
OCP-stubs/BRepTools/__init__.pyi
OCP-stubs/BRepTopAdaptor/__init__.pyi
OCP-stubs/BSplCLib/__init__.pyi
OCP-stubs/BSplSLib/__init__.pyi
OCP-stubs/BVH/__init__.pyi
OCP-stubs/BiTgte/__init__.pyi
OCP-stubs/BinDrivers/__init__.pyi
OCP-stubs/BinLDrivers/__init__.pyi
OCP-stubs/BinMDF/__init__.pyi
OCP-stubs/BinMDataStd/__init__.pyi
OCP-stubs/BinMDataXtd/__init__.pyi
OCP-stubs/BinMDocStd/__init__.pyi
OCP-stubs/BinMFunction/__init__.pyi
cadquery_ocp_stubs-7.8.1.1.post1.dist-info/METADATA
cadquery_ocp_stubs-7.8.1.1.post1.dist-info/WHEEL
cadquery_ocp_stubs-7.8.1.1.post1.dist-info/top_level.txt
cadquery_ocp_stubs-7.8.1.1.post1.dist-info/RECORD
