Metadata-Version: 2.2
Name: cadquery-ocp-stubs
Version: 7.8.1.1.post1
Summary: Typing stubs for cadquery-ocp based on the official CadQuery/OCP sources
Author: Bernhard Walter
Requires-Python: <3.14,>=3.10
